cocinero/__init__.py
cocinero/cli.py
cocinero/commands.py
cocinero/parsers.py
cocinero/plugins/__init__.py
cocinero/plugins/execute.py
cocinero/plugins/rename.py
cocinero/plugins/replace.py
cocinero/recipe.py
cocinero/repository.py
cocinero/requirements.py
cocinero/vars.py
docs/CONTRIBUTING.md
docs/RECIPE.md
cocinero-0.1.3.dist-info/entry_points.txt
cocinero-0.1.3.dist-info/LICENSE
cocinero-0.1.3.dist-info/WHEEL
cocinero-0.1.3.dist-info/METADATA
cocinero-0.1.3.dist-info/RECORD
