Metadata-Version: 2.1
Name: cocinero
Version: 0.1.3
Summary: Um utilitário em Python para criar projetos a partir de templates
Home-page: https://github.com/desk467/cocinero
License: GPL-3.0-only
Keywords: devops,automation,boilerplate
Author: Ricardo Gomes
Author-email: desk467@gmail.com
Requires-Python: >=3.8,<4.0
Classifier: Development Status :: 2 - Pre-Alpha
Classifier: License :: OSI Approved :: GNU General Public License v3 (GPLv3)
Classifier: Programming Language :: Python :: 3
Classifier: Programming Language :: Python :: 3 :: Only
Classifier: Programming Language :: Python :: 3.8
Classifier: Topic :: Software Development
Classifier: Topic :: Utilities
Requires-Dist: Jinja2 (>=2.11.2,<3.0.0)
Requires-Dist: PyYAML (>=5.3.1,<6.0.0)
Requires-Dist: click (>=7.1.2,<8.0.0)
Requires-Dist: colorama (>=0.4.3,<0.5.0)
Requires-Dist: rich (>=1.1.0,<2.0.0)
Project-URL: Repository, https://github.com/desk467/cocinero
